MakeSens/MakeSens.py
MakeSens/__init__.py
MakeSens/__main__.py
MakeSens/test.py
MakeSens_API-0.5.1.dist-info/METADATA
MakeSens_API-0.5.1.dist-info/WHEEL
MakeSens_API-0.5.1.dist-info/entry_points.txt
MakeSens_API-0.5.1.dist-info/top_level.txt
MakeSens_API-0.5.1.dist-info/RECORD
