Metadata-Version: 2.1
Name: MakeSens-API
Version: 0.5.1
Summary: MakeSense API
Home-page: https://github.com/Ciencia-de-datos/API_Python/tree/main/MakeSensCloud-base
Author: MakeSens Maximiliano G.Ch. DAPL
Author-email: jose.salamancacoy@gmail.com
License: GNU General Public License v3.0
Platform: UNKNOWN
Classifier: Programming Language :: Python :: 3
Classifier: Programming Language :: Python :: 3.9
Requires-Dist: datetime
Requires-Dist: pandas
Requires-Dist: requests
Requires-Dist: typing
